gh_commander-0.1.0.dev68.data/data/EGG-INFO/LICENSE
gh_commander-0.1.0.dev68.data/data/EGG-INFO/README.md
gh_commander/_compat.py
gh_commander/__main__.py
gh_commander/commands.py
gh_commander/config.py
gh_commander/__init__.py
gh_commander-0.1.0.dev68.dist-info/top_level.txt
gh_commander-0.1.0.dev68.dist-info/RECORD
gh_commander-0.1.0.dev68.dist-info/WHEEL
gh_commander-0.1.0.dev68.dist-info/metadata.json
gh_commander-0.1.0.dev68.dist-info/entry_points.txt
gh_commander-0.1.0.dev68.dist-info/DESCRIPTION.rst
gh_commander-0.1.0.dev68.dist-info/METADATA
