Metadata-Version: 2.0
Name: gh-commander
Version: 0.1.0.dev68
Summary: GitHub Commander – A tool to access the GitHub APIv3 from the CLI and automate otherwise tedious tasks.
Home-page: https://github.com/jhermann/gh-commander
Author: Jürgen Hermann
Author-email: jh@web.de
License: Apache 2.0
Keywords: hosted.by.github,github,cli,tool,automation
Platform: UNKNOWN
Classifier: Development Status :: 3 - Alpha
Classifier: Environment :: Console
Classifier: License :: OSI Approved :: Apache Software License
Classifier: Intended Audience :: Developers
Classifier: Operating System :: OS Independent
Classifier: Topic :: Software Development
Classifier: Topic :: Software Development :: Version Control
Classifier: Topic :: Utilities
Classifier: Programming Language :: Python :: 2
Classifier: Programming Language :: Python :: 2.7
Classifier: Programming Language :: Python :: 3
Classifier: Programming Language :: Python :: 3.4
Requires-Dist: click (==3.3)
Requires-Dist: colorama (==0.3.3)
Requires-Dist: PyGithub (==1.25.2)
